{
  "name": "Producto",
  "base": "PersistedModel",
  "idInjection": true,
  "options": {
    "validateUpsert": true
  },
  "properties": {
    "nombre": {
      "type": "string",
      "required": true
    },
    "comprar": {
      "type": "boolean",
      "required": true,
      "default": false
    }
  },
  "validations": [],
  "relations": {
    "listaFamiliar": {
      "type": "belongsTo",
      "model": "ListaFamiliar",
      "foreignKey": ""
    }
  },
  "acls": [
    {
      "accessType": "EXECUTE",
      "principalType": "ROLE",
      "principalId": "$authenticated",
      "permission": "ALLOW",
      "property": "limpiarLista"
    }
  ],
  "methods": {
    "limpiarLista": {
      "accepts": [
        {
          "arg": "context",
          "type": "object",
          "required": true,
          "description": "contexto",
          "http": {
            "source": "context"
          }
        }
      ],
      "returns": [
        {
          "arg": "array",
          "type": "array",
          "root": true,
          "description": "lista de productos"
        }
      ],
      "description": "pone a todos los productos pertenecientes a una lista en false",
      "http": [
        {
          "path": "/limpiarLista",
          "verb": "put"
        }
      ]
    }
  }
}
